{"frames":{"box_top_dmg_kalmar":{"frame":{"x":1,"y":1,"w":550,"h":530},"sourceSize":{"w":550,"h":530}},"boss12_body":{"frame":{"x":553,"y":1,"w":317,"h":518},"sourceSize":{"w":317,"h":518}},"boss2_telo":{"frame":{"x":1,"y":533,"w":389,"h":484},"sourceSize":{"w":389,"h":484}},"boss10_body":{"frame":{"x":392,"y":533,"w":285,"h":470},"sourceSize":{"w":285,"h":470}},"karabas_body_up":{"frame":{"x":679,"y":533,"w":296,"h":387},"sourceSize":{"w":296,"h":387}}},"meta":{"app":"PixiAnimate","scale":1,"image":"fights_elements_atlas_14.png","size":{"w":1024,"h":1024}}}